scarap/README.md
scarap/__init__.py
scarap/__main__.py
scarap/callers.py
scarap/checkers.py
scarap/computers.py
scarap/helpers.py
scarap/module_wrappers.py
scarap/modules.py
scarap/pan.py
scarap/readerswriters.py
scarap/utils.py
scarap/tests/test_check_mmseqs.py
scarap/tests/test_cn_rooting.py
scarap/tests/test_ficlin.py
scarap/tests/test_superfamily_splitting.py
scarap/tests/test_tree_rooting.py
scarap-1.0.1.dist-info/licenses/LICENSE
scarap-1.0.1.dist-info/METADATA
scarap-1.0.1.dist-info/WHEEL
scarap-1.0.1.dist-info/entry_points.txt
scarap-1.0.1.dist-info/top_level.txt
scarap-1.0.1.dist-info/RECORD
