Metadata-Version: 2.4
Name: scarap
Version: 1.0.1
Summary: A toolkit for prokaryotic comparative genomics
Author-email: Stijn Wittouck <stijn.wittouck@uantwerpen.be>
Maintainer-email: Stijn Wittouck <stijn.wittouck@uantwerpen.be>, Tim Van Rillaer <tim.vanrillaer@uantwerpen.be>
Project-URL: Homepage, https://github.com/SWittouck/SCARAP
Project-URL: Issues, https://github.com/SWittouck/SCARAP/issues
Classifier: Programming Language :: Python :: 3
Classifier: License :: OSI Approved :: GNU General Public License v3 (GPLv3)
Classifier: Operating System :: OS Independent
Requires-Python: <3.13,>=3.6.7
License-File: LICENSE
Requires-Dist: wheel
Requires-Dist: biopython>=1.67
Requires-Dist: ete3>=3.1.1
Requires-Dist: numpy>=1.16.5
Requires-Dist: scipy>=1.4.1
Requires-Dist: pandas
Dynamic: license-file
